steroid/__init__.py
steroid/app.py
steroid/constants.py
steroid/controller.py
steroid/logging.py
steroid/methods.py
steroid/middleware.py
steroid/utils.py
steroid-0.16b0.dist-info/LICENSE
steroid-0.16b0.dist-info/METADATA
steroid-0.16b0.dist-info/WHEEL
steroid-0.16b0.dist-info/RECORD
